LICENCE.txt
MANIFEST.in
README.rst
setup.cfg
setup.py
diags/__init__.py
diags/django.py
diags/icons.py
diags/processors.py
diags/resolver.py
diags/workflow.py
project_composer/__init__.py
project_composer/compose.py
project_composer/defaults.py
project_composer/exceptions.py
project_composer/helpers.py
project_composer/importer.py
project_composer/logger.py
project_composer/marker.py
project_composer.egg-info/PKG-INFO
project_composer.egg-info/SOURCES.txt
project_composer.egg-info/dependency_links.txt
project_composer.egg-info/entry_points.txt
project_composer.egg-info/requires.txt
project_composer.egg-info/top_level.txt
project_composer.egg-info/zip-safe
project_composer/app_storage/__init__.py
project_composer/app_storage/node.py
project_composer/app_storage/store.py
project_composer/cli/__init__.py
project_composer/cli/base_options.py
project_composer/cli/entrypoint.py
project_composer/cli/purge.py
project_composer/cli/requirements.py
project_composer/cli/version.py
project_composer/contrib/__init__.py
project_composer/contrib/django/__init__.py
project_composer/contrib/django/collector.py
project_composer/contrib/django/helpers.py
project_composer/contrib/django/processors.py
project_composer/manifest/__init__.py
project_composer/manifest/base.py
project_composer/manifest/fields.py
project_composer/manifest/manifesto.py
project_composer/manifest/plugins.py
project_composer/processors/__init__.py
project_composer/processors/base.py
project_composer/processors/classes.py
project_composer/processors/purge.py
project_composer/processors/text.py
project_composer/utils/__init__.py
project_composer/utils/encoding.py
project_composer/utils/tests.py
project_composer/utils/tree_printer.py